colorpycker/__init__.py
colorpycker/colorpycker.svg
colorpycker/config.py
colorpycker/floatingwidget.py
colorpycker/historywindow.py
colorpycker-1.0.0.dist-info/LICENSE
colorpycker-1.0.0.dist-info/METADATA
colorpycker-1.0.0.dist-info/WHEEL
colorpycker-1.0.0.dist-info/entry_points.txt
colorpycker-1.0.0.dist-info/top_level.txt
colorpycker-1.0.0.dist-info/RECORD
