Metadata-Version: 2.1
Name: colorpycker
Version: 1.0.0
Summary: A simple color picker written in Qt
Project-URL: Homepage, https://github.com/transistxr/colorpycker
Project-URL: Issues, https://github.com/transistxr/colorpycker/issues
License-File: LICENSE
Requires-Dist: PySide6
Requires-Dist: PyYAML
